Markdown_renderer/__init__.py
Markdown_renderer/markdownrenderer.py
markdownrenderer-1.0.dist-info/LICENSE
markdownrenderer-1.0.dist-info/METADATA
markdownrenderer-1.0.dist-info/WHEEL
markdownrenderer-1.0.dist-info/top_level.txt
markdownrenderer-1.0.dist-info/RECORD
